{
  "ts": "2026-04-17T11:15:01.336386",
  "generated": "11:15:01 AM",
  "paper": {
    "equity": 101107.47,
    "cash": 95691.27,
    "day_pnl": 213.88,
    "day_pnl_pct": 0.212,
    "positions": [
      {
        "sym": "CSX",
        "qty": 98.7143,
        "price": 43.55,
        "entry": 42.423094,
        "pnl_pct": 2.66,
        "pnl": 111.24,
        "mkt_val": 4299.01
      },
      {
        "sym": "ETHUSD",
        "qty": 0.456585675,
        "price": 2446.851,
        "entry": 2318.61,
        "pnl_pct": 5.53,
        "pnl": 58.55,
        "mkt_val": 1117.2
      }
    ]
  },
  "live": {
    "equity": 50.0,
    "cash": 50.0,
    "day_pnl": 0.0,
    "status": "FUNDED",
    "positions": []
  },
  "challenger": {
    "value": 100.0,
    "return_pct": 0.0,
    "milestone": "START",
    "trades": 0,
    "win_rate": 0.0
  }
}