{
  "ts": "2026-04-27T15:00:01.011484",
  "generated": "03:00:01 PM",
  "paper": {
    "equity": 101265.95,
    "cash": 100220.23,
    "day_pnl": -13.1,
    "day_pnl_pct": -0.013,
    "positions": [
      {
        "sym": "ETHUSD",
        "qty": 0.456585675,
        "price": 2290.31,
        "entry": 2318.61,
        "pnl_pct": -1.22,
        "pnl": -12.92,
        "mkt_val": 1045.72
      }
    ]
  },
  "live": {
    "equity": 50.0,
    "cash": 50.0,
    "day_pnl": 0.0,
    "status": "FUNDED",
    "positions": []
  },
  "challenger": {
    "value": 100.0,
    "return_pct": 0.0,
    "milestone": "START",
    "trades": 0,
    "win_rate": 0.0
  }
}