{
  "ts": "2026-04-16T16:35:00.604534",
  "generated": "04:35:00 PM",
  "paper": {
    "equity": 100896.51,
    "cash": 89974.12,
    "day_pnl": 300.63,
    "day_pnl_pct": 0.299,
    "positions": [
      {
        "sym": "ANET",
        "qty": 9.0,
        "price": 160.6735,
        "entry": 154.398056,
        "pnl_pct": 4.06,
        "pnl": 56.48,
        "mkt_val": 1446.06
      },
      {
        "sym": "CSX",
        "qty": 196.7143,
        "price": 42.72,
        "entry": 42.423094,
        "pnl_pct": 0.7,
        "pnl": 58.41,
        "mkt_val": 8403.63
      },
      {
        "sym": "ETHUSD",
        "qty": 0.456585675,
        "price": 2349.3885,
        "entry": 2318.61,
        "pnl_pct": 1.33,
        "pnl": 14.05,
        "mkt_val": 1072.7
      }
    ]
  },
  "live": {
    "equity": 50.0,
    "cash": 50.0,
    "day_pnl": 0.0,
    "status": "FUNDED",
    "positions": []
  },
  "challenger": {
    "value": 100.0,
    "return_pct": 0.0,
    "milestone": "START",
    "trades": 0,
    "win_rate": 0.0
  }
}