{
  "ts": "2026-04-21T12:40:01.350877",
  "generated": "12:40:01 PM",
  "paper": {
    "equity": 101751.31,
    "cash": 95424.54,
    "day_pnl": 353.07,
    "day_pnl_pct": 0.348,
    "positions": [
      {
        "sym": "ETHUSD",
        "qty": 0.456585675,
        "price": 2317.216,
        "entry": 2318.61,
        "pnl_pct": -0.06,
        "pnl": -0.64,
        "mkt_val": 1058.01
      },
      {
        "sym": "ORCL",
        "qty": 28.6035,
        "price": 184.2,
        "entry": 176.76,
        "pnl_pct": 4.21,
        "pnl": 212.81,
        "mkt_val": 5268.76
      }
    ]
  },
  "live": {
    "equity": 50.0,
    "cash": 50.0,
    "day_pnl": 0.0,
    "status": "FUNDED",
    "positions": []
  },
  "challenger": {
    "value": 100.0,
    "return_pct": 0.0,
    "milestone": "START",
    "trades": 0,
    "win_rate": 0.0
  }
}