{
  "ts": "2026-04-17T10:20:00.811046",
  "generated": "10:20:00 AM",
  "paper": {
    "equity": 101067.44,
    "cash": 91430.23,
    "day_pnl": 173.85,
    "day_pnl_pct": 0.172,
    "positions": [
      {
        "sym": "CSX",
        "qty": 196.7143,
        "price": 43.35,
        "entry": 42.423094,
        "pnl_pct": 2.19,
        "pnl": 182.34,
        "mkt_val": 8527.56
      },
      {
        "sym": "ETHUSD",
        "qty": 0.456585675,
        "price": 2430.3,
        "entry": 2318.61,
        "pnl_pct": 4.82,
        "pnl": 51.0,
        "mkt_val": 1109.64
      }
    ]
  },
  "live": {
    "equity": 50.0,
    "cash": 50.0,
    "day_pnl": 0.0,
    "status": "FUNDED",
    "positions": []
  },
  "challenger": {
    "value": 100.0,
    "return_pct": 0.0,
    "milestone": "START",
    "trades": 0,
    "win_rate": 0.0
  }
}