{
  "ts": "2026-04-20T15:45:01.152273",
  "generated": "03:45:01 PM",
  "paper": {
    "equity": 101396.94,
    "cash": 85202.37,
    "day_pnl": 343.26,
    "day_pnl_pct": 0.34,
    "positions": [
      {
        "sym": "DELL",
        "qty": 25.7826,
        "price": 205.53,
        "entry": 196.93,
        "pnl_pct": 4.37,
        "pnl": 221.73,
        "mkt_val": 5299.1
      },
      {
        "sym": "ETHUSD",
        "qty": 0.456585675,
        "price": 2329.592,
        "entry": 2318.61,
        "pnl_pct": 0.47,
        "pnl": 5.01,
        "mkt_val": 1063.66
      },
      {
        "sym": "ORCL",
        "qty": 55.6035,
        "price": 176.83,
        "entry": 176.76,
        "pnl_pct": 0.04,
        "pnl": 3.89,
        "mkt_val": 9832.37
      }
    ]
  },
  "live": {
    "equity": 50.0,
    "cash": 50.0,
    "day_pnl": 0.0,
    "status": "FUNDED",
    "positions": []
  },
  "challenger": {
    "value": 100.0,
    "return_pct": 0.0,
    "milestone": "START",
    "trades": 0,
    "win_rate": 0.0
  }
}