{
  "ts": "2026-05-01T13:25:01.219087",
  "generated": "01:25:01 PM",
  "paper": {
    "equity": 101344.3,
    "cash": 94061.46,
    "day_pnl": -26.34,
    "day_pnl_pct": -0.026,
    "positions": [
      {
        "sym": "SLB",
        "qty": 128.5018,
        "price": 56.675,
        "entry": 56.5,
        "pnl_pct": 0.31,
        "pnl": 22.49,
        "mkt_val": 7282.84
      }
    ]
  },
  "live": {
    "equity": 0.0,
    "cash": 0.0,
    "day_pnl": 0.0,
    "status": "PENDING_DEPOSIT",
    "positions": []
  },
  "challenger": {
    "value": 100.0,
    "return_pct": 0.0,
    "milestone": "START",
    "trades": 0,
    "win_rate": 0.0
  }
}